<annotation>
	<folder>fisk</folder>
	<filename>2022-05-01_133736_518076.jpg</filename>
	<path>C:\tmp\fisk\2022-05-01_133736_518076.jpg</path>
	<source>
		<database>Unknown</database>
	</source>
	<size>
		<width>4096</width>
		<height>2160</height>
		<depth>3</depth>
	</size>
	<segmented>0</segmented>
	<object>
		<name>salmon</name>
		<pose>Unspecified</pose>
		<truncated>0</truncated>
		<difficult>0</difficult>
		<bndbox>
			<xmin>1134</xmin>
			<ymin>1176</ymin>
			<xmax>3285</xmax>
			<ymax>1871</ymax>
		</bndbox>
	</object>
</annotation>
